klrr/__init__.py
klrr/klrr.py
klrr-0.1.dist-info/METADATA
klrr-0.1.dist-info/WHEEL
klrr-0.1.dist-info/top_level.txt
klrr-0.1.dist-info/RECORD
