Metadata-Version: 2.1
Name: klrr
Version: 0.1
Summary: The Goal Of This Library Is To Help Students to learn programming
